htrflow_cookie/__init__.py
htrflow_cookie/main.py
htrflow_cookie/py.typed
htrflow_cookie-0.0.4.dist-info/LICENSE
htrflow_cookie-0.0.4.dist-info/METADATA
htrflow_cookie-0.0.4.dist-info/WHEEL
htrflow_cookie-0.0.4.dist-info/RECORD
