Metadata-Version: 2.1
Name: htrflow_cookie
Version: 0.0.4
Summary: A short description of the project
Home-page: https://github.com/Swedish-National-Archives-AI-lab/htrflow_cookie
License: MIT
Author: Swedish-National-Archives-AI-lab
Author-email: gabriel.borg@riksarkivet.se
Requires-Python: >=3.10,<4.0
Classifier: Development Status :: 4 - Beta
Classifier: Intended Audience :: Developers
Classifier: License :: OSI Approved :: MIT License
Classifier: Operating System :: OS Independent
Classifier: Programming Language :: Python
Classifier: Programming Language :: Python :: 3
Classifier: Programming Language :: Python :: 3.10
Classifier: Programming Language :: Python :: 3.11
Classifier: Programming Language :: Python :: 3.12
Classifier: Topic :: Software Development :: Libraries :: Python Modules
Classifier: Typing :: Typed
Requires-Dist: pandas
Project-URL: Documentation, https://Swedish-National-Archives-AI-lab.github.io/htrflow_cookie
Project-URL: Repository, https://github.com/Swedish-National-Archives-AI-lab/htrflow_cookie
